dservercore/__init__.py
dservercore/annotations_routes.py
dservercore/base_uri_routes.py
dservercore/blueprint.py
dservercore/cli.py
dservercore/config.py
dservercore/config_routes.py
dservercore/date_utils.py
dservercore/extensions.py
dservercore/manifest_routes.py
dservercore/me_routes.py
dservercore/readme_routes.py
dservercore/schemas.py
dservercore/sort.py
dservercore/sql_models.py
dservercore/tags_routes.py
dservercore/uri_routes.py
dservercore/user_routes.py
dservercore/utils.py
dservercore/utils_auth.py
dservercore/uuid_routes.py
dservercore/version.py
dservercore/templates/index.html
dservercore-0.22.0.dist-info/licenses/LICENSE
dservercore-0.22.0.dist-info/METADATA
dservercore-0.22.0.dist-info/WHEEL
dservercore-0.22.0.dist-info/entry_points.txt
dservercore-0.22.0.dist-info/top_level.txt
dservercore-0.22.0.dist-info/RECORD
