Metadata-Version: 2.4
Name: dservercore
Version: 0.22.0
Summary: Web API to register/lookup/search for dtool dataset metadata
Author-email: Tjelvar Olsson <tjelvar.olsson@gmail.com>
License: MIT License
Project-URL: Documentation, https://dservercore.readthedocs.io
Project-URL: Repository, https://github.com/jic-dtool/dservercore
Project-URL: Changelog, https://github.com/jic-dtool/dservercore/blob/main/CHANGELOG.rst
License-File: LICENSE
Requires-Dist: setuptools
Requires-Dist: flask<3
Requires-Dist: pymongo
Requires-Dist: alembic
Requires-Dist: flask-sqlalchemy
Requires-Dist: flask-migrate
Requires-Dist: flask-pymongo
Requires-Dist: flask-marshmallow
Requires-Dist: flask-smorest
Requires-Dist: marshmallow-sqlalchemy
Requires-Dist: flask-cors
Requires-Dist: dtoolcore>=3.18.0
Requires-Dist: flask-jwt-extended[asymmetric_crypto]>=4.6.0
Requires-Dist: pyyaml
Provides-Extra: test
Requires-Dist: pytest; extra == "test"
Requires-Dist: pytest-cov; extra == "test"
Provides-Extra: docs
Requires-Dist: sphinx; extra == "docs"
Requires-Dist: sphinx_rtd_theme; extra == "docs"
Requires-Dist: sphinxcontrib-spelling; extra == "docs"
Requires-Dist: myst-parser==4.0.0; extra == "docs"
Dynamic: license-file
